Metadata-Version: 2.1
Name: Adversarials
Version: 1.0.1
Summary: easy wrapper for initializing several GAN networks in keras
Home-page: https://github.com/deven96/Simple_GAN
Author: Domnan Diretnan, Victor Afolabi
Author-email: diretnandomnan@gmail.com, javafolabi@gmail.com
License: MIT
Keywords: keras GAN GANs networks adversarial
Platform: UNKNOWN
Classifier: Programming Language :: Python :: 3
Classifier: License :: OSI Approved :: MIT License
Classifier: Operating System :: OS Independent
